[{
	"avatar": "https://eternitywith.github.io/medias/avatar.jpg",
	"name": "百念成诗",
	"introduction": "世界以痛吻我，要我报之以歌",
	"url": "https://www.eternitywith.xyz/",
	"title": "前去学习"
}, {
	"avatar": "https://cdn.jsdelivr.net/gh/small-rose/small-rose.github.io@master/medias/avatar.jpg",
	"name": "Small-Rose",
	"introduction": "JAVA WEB | 道虽迩，不行不至；事虽小，不为不成。",
	"url": "https://zhangxiaocai.cn/",
	"title": "访问主页"
},{
	"avatar": "https://cdn.jsdelivr.net/gh/amehime/shoka@latest/images/avatar.jpg",
	"name": "優萌初華",
	"introduction": "琉璃的医学 & 编程笔记",
	"url": "https://shoka.lostyu.me/",
	"title": "访问主页"
}, {
	"avatar": "https://gitee.com/yafine66/blogimage/raw/master/img/me.jpg",
	"name": "过客～励む",
	"introduction": "你现在的努力，是为了以后有更多的选择!",
	"url": "https://yafine-blog.cn",
	"title": "访问主页"
}, {
	"avatar": "https://cdn.jsdelivr.net/gh/xiaopengand/xiaopengand.github.io/medias/avatar.jpg",
	"name": "Xpand",
	"introduction": "月亮很亮,亮也没用",
	"url": "https://www.qwas.top",
	"title": "前去观摩"
}, {
	"avatar": "https://hesifan.top/medias/avatar.jpg",
	"name": "凡尘纪",
	"introduction": "念念不忘 必有回响",
	"url": "https://hesifan.top",
	"title": "访问主页"
}, {
	"avatar": "https://mx142.cn/medias/logo.png",
	"name": "Mx",
	"introduction": "一个分享知识和快乐的地方！",
	"url": "https://mx142.cn",
	"title": "访问主页"
}, {
	"avatar": "https://nekodeng.gitee.io/medias/avatar.jpg",
	"name": "itsNekoDeng",
	"introduction": "十万伏特皮卡丘，梦想是世界和平，想要发光发热",
	"url": "https://nekodeng.gitee.io",
	"title": "访问主页"
}, {
	"avatar": "https://cdn.jsdelivr.net/gh/Tajang-ctf/blog_images/avatar.jpg",
	"name": "Tajang",
	"introduction": "专注于网络安全与CTF",
	"url": "https://www.ctfking.com",
	"title": "前去学习"
}, {
	"avatar": "https://cdn2.sublimerui.top/2021/01/03/5db7a51e823a6.ico",
	"name": "果子酱",
	"introduction": "业精于勤，荒于嬉；行成于思，毁于随",
	"url": "https://cwxyr.me",
	"title": "访问主页"
}, {
	"avatar": "https://ying626.top/img/headPortrait.jpg",
	"name": "郭祥迎Blog",
	"introduction": "热爱生活，热爱交友",
	"url": "https://ying626.top",
	"title": "访问主页"
}, {
	"avatar": "https://txc.gtimg.com/data/298698/2020/1212/8ba6b3fe09630e500c7dcb5e848e22ed.jpeg",
	"name": "南瓜奶酪",
	"introduction": "让信念燃烧青春",
	"url": "https://chinawei.me",
	"title": "访问主页"
},{
	"avatar": "https://zfe.space/images/headimage.png",
	"name": "小冰博客",
	"introduction": "做个有梦想的人！",
	"url": "https://zfe.one",
	"title": "访问主页"
},{
	"avatar": "https://blog.adworld.top/photo/zhade2.jpg",
	"name": "云梦 ╮不浅",
	"introduction": "梦，开始的地方",
	"url": "https://blog.adworld.top/",
	"title": "访问主页"
},{
	"avatar": "https://q4.qlogo.cn/headimg_dl?dst_uin=1444440144&spec=100",
	"name": "Ch1e'sBlog",
	"introduction": "网络安全爱好者",
	"url": "https://qqblog.top",
	"title": "前去观摩"
},{
	"avatar": "https://ss1.bdstatic.com/70cFuXSh_Q1YnxGkpoWK1HF6hhy/it/u=3216471116,1483332883&fm=26&gp=0.jpg",
	"name": "SAM ‘S BOLG",
	"introduction": "一个杂七杂八的博客",
	"url": "http://sam1314.xyz:1314",
	"title": "前去观摩"
},{
	"avatar": "https://www.izhaoo.com/images/icons/favicon-32x32.png",
	"name": "zhaoo's Blog",
	"introduction": "izhaoo",
	"url": "https://www.izhaoo.com/",
	"title": "前去观摩"
},{
	"avatar": "https://q1.qlogo.cn/g?b=qq&nk=2085886325&s=640",
	"name": "不冷博客",
	"introduction": "听喜欢的歌，做喜欢的事",
	"url": "https://www.buleng.xyz",
	"title": "前去观摩"
}]